functions_by_elikanzharbek/README.md
functions_by_elikanzharbek/math_functions.py
functions_by_elikanzharbek-0.3.0.dist-info/WHEEL
functions_by_elikanzharbek-0.3.0.dist-info/METADATA
functions_by_elikanzharbek-0.3.0.dist-info/RECORD
